thousandwords/__init__.py
thousandwords/auth.py
thousandwords/capture.py
thousandwords/cli.py
thousandwords/client.py
thousandwords/config.py
thousandwords/credentials.py
thousandwords/lint.py
thousandwords/polling.py
thousandwords/publish.py
thousandwords/share.py
thousandwords/status.py
thousandwords-0.10.0.dist-info/entry_points.txt
thousandwords-0.10.0.dist-info/LICENSE
thousandwords-0.10.0.dist-info/WHEEL
thousandwords-0.10.0.dist-info/METADATA
thousandwords-0.10.0.dist-info/RECORD
